{
  "id": "10661",
  "slug": "stability-swiss-exercise-ball-dumbbell-chest-flyes",
  "title": "Stability / Swiss / Exercise Ball Dumbbell Chest Flyes",
  "description": "Gymnastic Ring L-Holds Resistance Band Push-ups / Pushups Double Side Jackknifes Browse all exercises Stability / swiss / exercise ball dumbbell chest flyes is a gym work out exercise that targets abs and chest and also involves shoulders and triceps. Refer to the illustration diagram and instructions above for how to perform this exercise correctly. Gymnastic ring l-holds, resistance band push-ups / pushups and double side jackknifes are related exercise that target the same muscle groups as stability / swiss / exercise ball dumbbell chest flyes. Visit our free illustrated exercise directory for more exercises to try in your workouts. Exercise illustration licensing: Our exercise and yoga pose illustrations (static and animated) are selectively available for licensing for commercial and non-commercial projects. Visit our exercise illustrations licensing page for detailed information and to submit in inquiry. Our exercise illustrations represent original artwork registered with and protected by the U.S. Copyright Office. Unauthorized use violators will be prosecuted. More details.",
  "equipment": [
    "Swiss / Exercise Ball"
  ],
  "primary_muscles": [
    "Abs",
    "Chest"
  ],
  "secondary_muscles": [
    "Shoulders",
    "Triceps"
  ],
  "related_exercises": [
    "Gymnastic Ring L-Holds",
    "Resistance Band Push-ups / Pushups",
    "Double Side Jackknifes"
  ],
  "images": {
    "male": "https://workoutlabs.com/train/svg.php?id=84449",
    "female": "https://workoutlabs.com/train/svg.php?id=85233"
  }
}