{
  "id": "3448",
  "slug": "medicine-ball-push-ups",
  "title": "Medicine Ball Push-Ups",
  "description": "Wall Push-Ups / Pushups / Standing Press Ups Stability / Swiss / Exercise Ball Pushups / Push-ups Spiderman Push-ups / Pushups Browse all exercises Medicine ball push-ups is a gym work out exercise that targets chest and also involves abs and shoulders and triceps. Refer to the illustration diagram and instructions above for how to perform this exercise correctly. Wall push-ups / pushups / standing press ups, stability / swiss / exercise ball pushups / push-ups and spiderman push-ups / pushups are related exercise that target the same muscle groups as medicine ball push-ups. Visit our free illustrated exercise directory for more exercises to try in your workouts. Exercise illustration licensing: Our exercise and yoga pose illustrations (static and animated) are selectively available for licensing for commercial and non-commercial projects. Visit our exercise illustrations licensing page for detailed information and to submit in inquiry. Our exercise illustrations represent original artwork registered with and protected by the U.S. Copyright Office. Unauthorized use violators will be prosecuted. More details.",
  "equipment": [
    "Medicine Ball"
  ],
  "primary_muscles": [
    "Chest"
  ],
  "secondary_muscles": [
    "Abs",
    "Shoulders",
    "Triceps"
  ],
  "related_exercises": [
    "Spiderman Push-ups / Pushups"
  ],
  "images": {
    "male": "https://workoutlabs.com/train/svg.php?id=84256",
    "female": "https://workoutlabs.com/train/svg.php?id=85042"
  }
}