{
  "id": "19121",
  "slug": "swiss-exercise-ball-reverse-crunches",
  "title": "Stability / Swiss / Exercise Ball Reverse Crunches",
  "description": "Gymnastic Ring L-Holds Browse all exercises Stability / swiss / exercise ball reverse crunches is a gym work out exercise that targets abs and obliques and also involves glutes & hip flexors. Refer to the illustration diagram and instructions above for how to perform this exercise correctly. Stability / swiss / exercise ball dumbbell chest flyes, gymnastic ring l-holds and reverse crunch are related exercise that target the same muscle groups as stability / swiss / exercise ball reverse crunches. Visit our free illustrated exercise directory for more exercises to try in your workouts. Exercise illustration licensing: Our exercise and yoga pose illustrations (static and animated) are selectively available for licensing for commercial and non-commercial projects. Visit our exercise illustrations licensing page for detailed information and to submit in inquiry. Our exercise illustrations represent original artwork registered with and protected by the U.S. Copyright Office. Unauthorized use violators will be prosecuted. More details. Illustration licensing",
  "equipment": [
    "Swiss / Exercise Ball"
  ],
  "primary_muscles": [
    "Abs",
    "Obliques"
  ],
  "secondary_muscles": [
    "Glutes & Hip Flexors"
  ],
  "related_exercises": [
    "Gymnastic Ring L-Holds",
    "Reverse Crunch"
  ],
  "images": {
    "male": "https://workoutlabs.com/train/svg.php?id=84498",
    "female": "https://workoutlabs.com/train/svg.php?id=85281"
  }
}